brails/__init__.py
brails/constants.py
brails/exceptions.py
brails/py.typed
brails/filters/__init__.py
brails/filters/filter.py
brails/filters/house_view/__init__.py
brails/filters/house_view/house_view.py
brails/filters/house_view/groundingdino/__init__.py
brails/filters/house_view/groundingdino/version.py
brails/filters/house_view/groundingdino/config/GroundingDINO_SwinB.py
brails/filters/house_view/groundingdino/config/GroundingDINO_SwinT_OGC.py
brails/filters/house_view/groundingdino/config/__init__.py
brails/filters/house_view/groundingdino/datasets/__init__.py
brails/filters/house_view/groundingdino/datasets/transforms.py
brails/filters/house_view/groundingdino/models/__init__.py
brails/filters/house_view/groundingdino/models/registry.py
brails/filters/house_view/groundingdino/models/GroundingDINO/__init__.py
brails/filters/house_view/groundingdino/models/GroundingDINO/bertwarper.py
brails/filters/house_view/groundingdino/models/GroundingDINO/fuse_modules.py
brails/filters/house_view/groundingdino/models/GroundingDINO/groundingdino.py
brails/filters/house_view/groundingdino/models/GroundingDINO/ms_deform_attn.py
brails/filters/house_view/groundingdino/models/GroundingDINO/transformer.py
brails/filters/house_view/groundingdino/models/GroundingDINO/transformer_vanilla.py
brails/filters/house_view/groundingdino/models/GroundingDINO/utils.py
brails/filters/house_view/groundingdino/models/GroundingDINO/backbone/__init__.py
brails/filters/house_view/groundingdino/models/GroundingDINO/backbone/backbone.py
brails/filters/house_view/groundingdino/models/GroundingDINO/backbone/position_encoding.py
brails/filters/house_view/groundingdino/models/GroundingDINO/backbone/swin_transformer.py
brails/filters/house_view/groundingdino/util/__init__.py
brails/filters/house_view/groundingdino/util/box_ops.py
brails/filters/house_view/groundingdino/util/get_tokenlizer.py
brails/filters/house_view/groundingdino/util/inference.py
brails/filters/house_view/groundingdino/util/logger.py
brails-4.1.4.dist-info/licenses/LICENSE.txt
brails-4.1.4.dist-info/METADATA
brails-4.1.4.dist-info/WHEEL
brails-4.1.4.dist-info/top_level.txt
brails-4.1.4.dist-info/RECORD
