Metadata-Version: 2.4
Name: brails
Version: 4.1.4
Summary: BRAILS++: Building Regional Asset Inventories for Large Scale Simulation
Author: NHERI SimCenter
Author-email: NHERI SimCenter <nheri-simcenter@berkeley.edu>
License: BSD-3-Clause
Platform: any
Classifier: Programming Language :: Python
Classifier: Development Status :: 5 - Production/Stable
Classifier: Natural Language :: English
Classifier: Environment :: Console
Classifier: Framework :: Jupyter
Classifier: Intended Audience :: Education
Classifier: Intended Audience :: Science/Research
Classifier: License :: OSI Approved :: BSD License
Classifier: Operating System :: Microsoft :: Windows
Classifier: Operating System :: MacOS :: MacOS X
Classifier: Operating System :: Unix
Classifier: Programming Language :: Python :: 3.7
Classifier: Programming Language :: Python :: 3.8
Classifier: Programming Language :: Python :: 3.9
Classifier: Programming Language :: Python :: 3.10
Classifier: Programming Language :: Python :: 3.11
Classifier: Programming Language :: Python :: 3.12
Classifier: Topic :: Scientific/Engineering
Requires-Python: >=3.7
License-File: LICENSE.txt
Requires-Dist: addict
Requires-Dist: Cython
Requires-Dist: ftfy
Requires-Dist: matplotlib
Requires-Dist: opencv-python
Requires-Dist: pandas
Requires-Dist: pillow
Requires-Dist: plotly
Requires-Dist: pycocotools
Requires-Dist: pyarrow
Requires-Dist: rasterio
Requires-Dist: reverse-geocode
Requires-Dist: requests
Requires-Dist: scikit-learn
Requires-Dist: seaborn
Requires-Dist: shapely
Requires-Dist: supervision
Requires-Dist: numpy<2.0
Requires-Dist: timm
Requires-Dist: tensorboard
Requires-Dist: tensorboardX
Requires-Dist: torch<=2.5.0
Requires-Dist: torchvision<=0.20.0
Requires-Dist: transformers
Requires-Dist: wget
Requires-Dist: yacs
Requires-Dist: webcolors
Requires-Dist: yapf
Provides-Extra: development
Requires-Dist: flake8; extra == "development"
Requires-Dist: pylint; extra == "development"
Requires-Dist: black; extra == "development"
Requires-Dist: pytest; extra == "development"
Requires-Dist: pytest-cov; extra == "development"
Requires-Dist: jupyter; extra == "development"
Requires-Dist: jupytext; extra == "development"
Requires-Dist: sphinx; extra == "development"
Requires-Dist: sphinx-autoapi; extra == "development"
Requires-Dist: nbsphinx; extra == "development"
Requires-Dist: flake8-rst; extra == "development"
Requires-Dist: flake8-rst-docstrings; extra == "development"
Dynamic: author
Dynamic: description
Dynamic: license-file
Dynamic: platform
Dynamic: requires-dist
